{
  "unversionedId": "tutorials/cloth-parsing",
  "id": "tutorials/cloth-parsing",
  "title": "cloth-parsing",
  "description": "",
  "source": "@site/docs/tutorials/cloth-parsing.md",
  "sourceDirName": "tutorials",
  "slug": "/tutorials/cloth-parsing",
  "permalink": "/docs/tutorials/cloth-parsing",
  "editUrl": "https://github.com/recohut/docs/docs/docs/tutorials/cloth-parsing.md",
  "tags": [],
  "version": "current",
  "frontMatter": {
    "jupyter": {
      "jupytext": {
        "text_representation": {
          "extension": ".md",
          "format_name": "markdown",
          "format_version": "1.3",
          "jupytext_version": "1.13.7"
        }
      },
      "kernelspec": {
        "display_name": "Python 3",
        "name": "python3"
      }
    }
  },
  "sidebar": "tutorialSidebar",
  "previous": {
    "title": "cicd-docker-eks",
    "permalink": "/docs/tutorials/cicd-docker-eks"
  },
  "next": {
    "title": "clustering-data-into-groups-using-k-means-and-dbscan",
    "permalink": "/docs/tutorials/clustering-data-into-groups-using-k-means-and-dbscan"
  }
}