{
  "unversionedId": "tutorials/steam-game-recommender-lightfm-warp",
  "id": "tutorials/steam-game-recommender-lightfm-warp",
  "title": "steam-game-recommender-lightfm-warp",
  "description": "Loading steam video game data and performing EDA, ETL and training an implicit model based on WARP loss using LightFM library",
  "source": "@site/docs/tutorials/steam-game-recommender-lightfm-warp.md",
  "sourceDirName": "tutorials",
  "slug": "/tutorials/steam-game-recommender-lightfm-warp",
  "permalink": "/docs/tutorials/steam-game-recommender-lightfm-warp",
  "editUrl": "https://github.com/recohut/docs/docs/docs/tutorials/steam-game-recommender-lightfm-warp.md",
  "tags": [],
  "version": "current",
  "frontMatter": {
    "jupyter": {
      "jupytext": {
        "text_representation": {
          "extension": ".md",
          "format_name": "markdown",
          "format_version": "1.3",
          "jupytext_version": "1.13.7"
        }
      },
      "kernelspec": {
        "display_name": "Python 3",
        "name": "python3"
      }
    }
  },
  "sidebar": "tutorialSidebar",
  "previous": {
    "title": "statistics",
    "permalink": "/docs/tutorials/statistics"
  },
  "next": {
    "title": "stein",
    "permalink": "/docs/tutorials/stein"
  }
}