{
  "unversionedId": "tutorials/lda-topic-content-recommender",
  "id": "tutorials/lda-topic-content-recommender",
  "title": "lda-topic-content-recommender",
  "description": "Training LDA topic model on 20-newsgroups dataset and finding similar documents using KNN",
  "source": "@site/docs/tutorials/lda-topic-content-recommender.mdx",
  "sourceDirName": "tutorials",
  "slug": "/tutorials/lda-topic-content-recommender",
  "permalink": "/docs/tutorials/lda-topic-content-recommender",
  "editUrl": "https://github.com/recohut/docs/docs/docs/tutorials/lda-topic-content-recommender.mdx",
  "tags": [],
  "version": "current",
  "frontMatter": {
    "jupyter": {
      "jupytext": {
        "text_representation": {
          "extension": ".md",
          "format_name": "markdown",
          "format_version": "1.3",
          "jupytext_version": "1.13.7"
        }
      },
      "kernelspec": {
        "display_name": "Python 3",
        "name": "python3"
      }
    }
  },
  "sidebar": "tutorialSidebar",
  "previous": {
    "title": "lastfm-session",
    "permalink": "/docs/tutorials/lastfm-session"
  },
  "next": {
    "title": "learn-embeddings-using-graph-networks",
    "permalink": "/docs/tutorials/learn-embeddings-using-graph-networks"
  }
}